hello_meghana/__init__.py
hello_meghana/cli.py
hello_meghana2-0.4.dist-info/METADATA
hello_meghana2-0.4.dist-info/WHEEL
hello_meghana2-0.4.dist-info/entry_points.txt
hello_meghana2-0.4.dist-info/top_level.txt
hello_meghana2-0.4.dist-info/RECORD
