Metadata-Version: 2.1
Name: hello-meghana2
Version: 0.4
Summary: A simple World package
Home-page: UNKNOWN
Author: megha
Author-email: meghanabl2112@gmail.com
License: UNKNOWN
Platform: UNKNOWN
Requires-Dist: click
